AUTHORS.txt
LICENSE.txt
MANIFEST.in
README.md
pyproject.toml
setup.py
PyScreeze.egg-info/PKG-INFO
PyScreeze.egg-info/SOURCES.txt
PyScreeze.egg-info/dependency_links.txt
PyScreeze.egg-info/requires.txt
PyScreeze.egg-info/top_level.txt
docs/Makefile
docs/conf.py
docs/index.rst
docs/make.bat
docs/roadmap.rst
docs/screenshot.rst
pyscreeze/__init__.py
tests/benchmarks.py
tests/test_pillow_unavailable.py
tests/test_pyscreeze.py