Metadata-Version: 2.1
Name: PyScreeze
Version: 0.1.29
Summary: A simple, cross-platform screenshot module for Python 2 and 3.
Home-page: https://github.com/asweigart/pyscreeze
Author: Al Sweigart
Author-email: al@inventwithpython.com
License: MIT
Keywords: screenshot screen screencap capture scrot screencapture image
Classifier: Development Status :: 4 - Beta
Classifier: Environment :: Win32 (MS Windows)
Classifier: Environment :: X11 Applications
Classifier: Environment :: MacOS X
Classifier: Intended Audience :: Developers
Classifier: License :: OSI Approved :: MIT License
Classifier: Operating System :: OS Independent
Classifier: Programming Language :: Python
Classifier: Programming Language :: Python :: 3
Classifier: Programming Language :: Python :: 3.4
Classifier: Programming Language :: Python :: 3.5
Classifier: Programming Language :: Python :: 3.6
Classifier: Programming Language :: Python :: 3.7
Classifier: Programming Language :: Python :: 3.8
Classifier: Programming Language :: Python :: 3.9
Classifier: Programming Language :: Python :: 3.10
Classifier: Programming Language :: Python :: 3.11
Classifier: Programming Language :: Python :: 3 :: Only
License-File: LICENSE.txt
License-File: AUTHORS.txt
